chanalyze/__init__.py
chanalyze/app.py
chanalyze/emoji.py
chanalyze/emoji.txt
chanalyze/msg.py
chanalyze/util.py
chanalyze/emoji_data/__init__.py
chanalyze/emoji_data/get.py
chanalyze/model/__init__.py
chanalyze/model/chat.py
chanalyze/model/message.py
chanalyze/model/msgDiff.py
chanalyze/model/msgInMinute.py
chanalyze/model/msgOnDate.py
chanalyze/model/timePeriod.py
chanalyze/model/user.py
chanalyze-0.3.9.dist-info/entry_points.txt
chanalyze-0.3.9.dist-info/LICENSE
chanalyze-0.3.9.dist-info/WHEEL
chanalyze-0.3.9.dist-info/METADATA
chanalyze-0.3.9.dist-info/RECORD
