Metadata-Version: 2.1
Name: chanalyze
Version: 0.3.9
Summary: A simple WhatsApp Chat Analyzer ( for both Private & Group chats ), made with <3
Home-page: https://itzmeanjan.github.io/chanalyze
License: UNKNOWN
Author: Anjan Roy
Author-email: anjanroy@yandex.com
Requires-Python: >=3.7
Classifier: Intended Audience :: End Users/Desktop
Classifier: License :: OSI Approved :: MIT License
Classifier: Programming Language :: Python :: 3
Requires-Dist: matplotlib
Requires-Dist: requests
Requires-Dist: ray
Requires-Dist: seaborn
Requires-Dist: wordcloud
Requires-Dist: flit ; extra == "dev"
Provides-Extra: dev
